{"id":"pasikonik-zielony","name":"Pasikonik zielony","latinName":"Tettigonia viridissima","habitat":"łąki, łany zbóż, zarośla, polany.","food":"owadożerny i roślinożerny, żywi się innymi owadami oraz owocami roślin.","chronotype":"samce w okresie letnim grają od południa do świtu.","activity":"aktywny od lipca do października.","development":"<p>w rozwoju nie występuje stadium poczwarki: z jaj złożonych w ziemi lub szparach kory wylęgają się larwy o wyglądzie zbliżonym do dorosłego osobnika, larwy przechodzą kilka wylinek.</p> <p>Na pierwszej parze skrzydeł czyli pokrywach samce posiadają narządy strydulacyjne umożliwiające wydawanie charakterystycznych dźwięków spowodowanych pocieraniem skrzydła o skrzydło. Nogi mają długie i silne z kolcami na goleniach dzięki którym mogą oddawać dalekie skoki, na przednich goleniach mieści się narząd słuchu.</p>","img":"pasikonik_zielony.jpg"}